{
  "topic": "augment",
  "category_id": "pop_culture_media_modern_life",
  "clue_frequency": 1,
  "seen_at_values": [
    400
  ],
  "source": "wikipedia",
  "title": "Augment",
  "url": "https://en.wikipedia.org/wiki/Augment",
  "retrieved_at": "2026-06-16T14:36:01.717Z",
  "summary": "Augment or augmentation may refer to:",
  "extract": "Augment or augmentation may refer to:",
  "citation": {
    "source": "wikipedia",
    "title": "Augment",
    "url": "https://en.wikipedia.org/wiki/Augment"
  }
}