{
  "topic": "a leap of faith",
  "category_id": "religion_mythology_philosophy",
  "clue_frequency": 1,
  "seen_at_values": [
    800
  ],
  "source": "wikipedia",
  "title": "Leap of faith",
  "url": "https://en.wikipedia.org/wiki/Leap_of_faith",
  "retrieved_at": "2026-06-26T13:57:02.784Z",
  "summary": "\nIn philosophy, a leap of faith is the act of believing in or accepting something not on the basis of reason. The phrase is commonly associated with Danish philosopher Søren Kierkegaard.",
  "extract": "In philosophy, a leap of faith is the act of believing in or accepting something not on the basis of reason. The phrase is commonly associated with Danish philosopher Søren Kierkegaard.",
  "citation": {
    "source": "wikipedia",
    "title": "Leap of faith",
    "url": "https://en.wikipedia.org/wiki/Leap_of_faith"
  }
}