{
  "topic": "the Apocrypha",
  "category_id": "religion_mythology_philosophy",
  "clue_frequency": 1,
  "seen_at_values": [
    800
  ],
  "source": "wikipedia",
  "title": "Biblical apocrypha",
  "url": "https://en.wikipedia.org/wiki/Biblical_apocrypha",
  "retrieved_at": "2026-07-11T14:18:00.312Z",
  "summary": "The Biblical apocrypha denotes the collection of ancient books, some of which are believed by some to be of doubtful origin, thought to have been written some time between 200 BC and 100 AD.",
  "extract": "The Biblical apocrypha (from Ancient Greek  ἀπόκρυφος  (apókryphos) 'hidden') denotes the collection of ancient books, some of which are believed by some to be of doubtful origin, thought to have been written some time between 200 BC and 100 AD.\nThe Catholic Church, Eastern Orthodox Church, Oriental Orthodox Church, and Assyrian Church of the East include some or all of the same texts within the body of their version of the Old Testament, with Catholics terming them deuterocanonical books. Traditional 80-book Protestant Bibles include fourteen books in an intertestamental section between the Old Testament and New Testament called the Apocrypha, deeming these useful for instruction, but non-canonical. Reflecting this view, the lectionaries of the Lutheran Churches and Anglican Communion include readings from the Apocrypha.",
  "citation": {
    "source": "wikipedia",
    "title": "Biblical apocrypha",
    "url": "https://en.wikipedia.org/wiki/Biblical_apocrypha"
  }
}