{
  "topic": "Lake Ladoga",
  "category_id": "geography",
  "subcategory_name": "Rivers, Lakes & Seas",
  "theme": "lake",
  "seed": true,
  "source": "wikipedia",
  "title": "Lake Ladoga",
  "url": "https://en.wikipedia.org/wiki/Lake_Ladoga",
  "extract": "Lake Ladoga is a freshwater lake located in the Republic of Karelia and Leningrad Oblast in northwestern Russia, in the vicinity of Saint Petersburg.\nIt is the largest lake located entirely in Europe, the second largest lake in Russia after Lake Baikal, and the 14th largest lake by area in the world. It is comparable in size to Lake Ontario. Ladoga Lacus, a methane lake on Saturn's moon Titan, is named after the lake.",
  "citation": {
    "source": "wikipedia",
    "title": "Lake Ladoga",
    "url": "https://en.wikipedia.org/wiki/Lake_Ladoga"
  }
}