{
  "topic": "Western Australia",
  "category_id": "geography",
  "clue_frequency": 1,
  "seen_at_values": [
    800
  ],
  "source": "wikipedia",
  "title": "Western Australia",
  "url": "https://en.wikipedia.org/wiki/Western_Australia",
  "retrieved_at": "2026-06-13T21:55:01.822Z",
  "summary": "Western Australia is the westernmost state of Australia. It is bounded by the Indian Ocean to the north and west, the Southern Ocean to the south, the Northern Territory to the north-east, and South Australia to the south-east. Western Australia is Australia's largest state, with a land area of 2,527,013 square kilometres (975,685 sq mi), and is also the second-largest subdivision of any country on Earth.",
  "extract": "Western Australia (commonly abbreviated as WA) is the westernmost state of Australia. It is bounded by the Indian Ocean to the north and west, the Southern Ocean to the south, the Northern Territory to the north-east, and South Australia to the south-east. Western Australia is Australia's largest state, with a land area of 2,527,013 square kilometres (975,685 sq mi), and is also the second-largest subdivision of any country on Earth.\nThe state has a diverse range of climates, including tropical conditions in the Kimberley, deserts in the interior (including the Great Sandy Desert, Little Sandy Desert, Gibson Desert, and Great Victoria Desert) and a Mediterranean climate on the south-west and southern coastal areas. As of June 2024, the state has 2.965 million inhabitants—10.9 percent of the national total. Over 90 percent of the state's population live in the south-west corner and around 80 percent live in the state capital Perth, leaving the remainder of the state sparsely populated. The Trans-Australian Railway and the Eyre Highway traverse the Nullarbor Plain in the state's south-east, providing the principal connection between Western Australia and the population centres in the eastern states.\nWestern Australia's Indigenous peoples have been present for tens of thousands of years. Dutch explorers visited Western Australia from the 17th century, with Dirk Hartog's 1616 expedition the first Europeans to make landfall. The British claimed Western Australia in 1827 and established the Swan River Colony with Perth as its capital in 1829. The Western Australian gold rushes of the late 19th century resulted in a significant population influx. The colony was granted responsible government in 1890, the last of the Australian colonies to become self-governing, and federated with the other colonies in 1901.\nThe state's mining sector is a key driver of the state economy. The late 20th century saw the development of the state's significant iron ore mining industry – the world's largest – as well as primarily offshore petroleum and natural gas resources. Gold mining retains a significant presence and many other mineral commodities are mined, with Perth being a major centre for associated services. Outside of mining, primary industry is the other significant contributor to the state's economy, including agriculture in the Wheatbelt and temperate southern coastal regions, pastoralism in marginal grassland areas, forestry in the south-west and fishing (including pearling and, historically, whaling).",
  "citation": {
    "source": "wikipedia",
    "title": "Western Australia",
    "url": "https://en.wikipedia.org/wiki/Western_Australia"
  }
}