{
  "topic": "a springboard",
  "category_id": "sports_games_leisure",
  "clue_frequency": 1,
  "seen_at_values": [
    200
  ],
  "source": "wikipedia",
  "title": "Springboard",
  "url": "https://en.wikipedia.org/wiki/Springboard",
  "retrieved_at": "2026-07-09T14:53:00.502Z",
  "summary": "A springboard or diving board is used for diving and is a board that is itself a spring, i.e. a linear flex-spring, of the cantilever type.",
  "extract": "A springboard or diving board is used for diving and is a board that is itself a spring, i.e. a linear flex-spring, of the cantilever type.\nSpringboards are commonly fixed by a hinge at one end (so they can be flipped up when not in use), and the other end usually hangs over a swimming pool, with a point midway between the hinge and the end resting on an adjustable fulcrum.",
  "citation": {
    "source": "wikipedia",
    "title": "Springboard",
    "url": "https://en.wikipedia.org/wiki/Springboard"
  }
}